.coveragerc
.testr.conf
AUTHORS
ChangeLog
HACKING.rst
LICENSE
MANIFEST.in
README.rst
openstack-common.conf
requirements.txt
setup.cfg
setup.py
test-requirements.txt
tox.ini
doc/source/conf.py
doc/source/index.rst
doc/source/api/index.rst
doc/source/devref/development.environment.rst
doc/source/devref/index.rst
doc/source/devref/unit.tests.rst
doc/source/man/ripcord-api.rst
doc/source/man/ripcord-manage.rst
etc/ripcord/ripcord.conf.sample
ripcord/__init__.py
ripcord/test.py
ripcord/version.py
ripcord.egg-info/PKG-INFO
ripcord.egg-info/SOURCES.txt
ripcord.egg-info/dependency_links.txt
ripcord.egg-info/entry_points.txt
ripcord.egg-info/requires.txt
ripcord.egg-info/top_level.txt
ripcord/api/__init__.py
ripcord/api/acl.py
ripcord/api/app.py
ripcord/api/config.py
ripcord/api/hooks.py
ripcord/api/middleware.py
ripcord/api/controllers/__init__.py
ripcord/api/controllers/root.py
ripcord/api/controllers/v1/__init__.py
ripcord/api/controllers/v1/base.py
ripcord/api/controllers/v1/controller.py
ripcord/api/controllers/v1/subscriber.py
ripcord/cmd/__init__.py
ripcord/cmd/api.py
ripcord/cmd/manage.py
ripcord/common/__init__.py
ripcord/common/config.py
ripcord/common/exception.py
ripcord/common/paths.py
ripcord/common/schema.py
ripcord/common/utils.py
ripcord/db/__init__.py
ripcord/db/api.py
ripcord/db/migration.py
ripcord/db/sqlalchemy/__init__.py
ripcord/db/sqlalchemy/api.py
ripcord/db/sqlalchemy/migration.py
ripcord/db/sqlalchemy/models.py
ripcord/db/sqlalchemy/migrate_repo/__init__.py
ripcord/db/sqlalchemy/migrate_repo/manage.py
ripcord/db/sqlalchemy/migrate_repo/migrate.cfg
ripcord/db/sqlalchemy/migrate_repo/versions/001_add_initial_tables.py
ripcord/db/sqlalchemy/migrate_repo/versions/002_Rename_subscriber_table.py
ripcord/db/sqlalchemy/migrate_repo/versions/003_Add_disabled_field_to_subscribers.py
ripcord/db/sqlalchemy/migrate_repo/versions/__init__.py
ripcord/openstack/__init__.py
ripcord/openstack/common/__init__.py
ripcord/openstack/common/excutils.py
ripcord/openstack/common/fileutils.py
ripcord/openstack/common/gettextutils.py
ripcord/openstack/common/importutils.py
ripcord/openstack/common/jsonutils.py
ripcord/openstack/common/local.py
