Metadata-Version: 1.1
Name: ripcord
Version: 0.0.1
Summary: Automatic call distributor (ACD) using Python and Redis
Home-page: UNKNOWN
Author: Paul Belanger
Author-email: paul.belanger@polybeacon.com
License: Apache-2
Platform: UNKNOWN
Classifier: Development Status :: 2 - Pre-Alpha
Classifier: Environment :: Console
Classifier: Intended Audience :: Information Technology
Classifier: Intended Audience :: System Administrators
Classifier: License :: OSI Approved :: Apache Software License
Classifier: Operating System :: POSIX :: Linux
Classifier: Programming Language :: Python
Classifier: Programming Language :: Python :: 2
Classifier: Programming Language :: Python :: 2.7
